CHANGES.txt
CONTRIBUTORS.txt
MANIFEST.in
README.rst
setup.py
docs/LICENSE.txt
src/requests_extensions/__init__.py
src/requests_extensions.adapters.egg-info/PKG-INFO
src/requests_extensions.adapters.egg-info/SOURCES.txt
src/requests_extensions.adapters.egg-info/dependency_links.txt
src/requests_extensions.adapters.egg-info/entry_points.txt
src/requests_extensions.adapters.egg-info/namespace_packages.txt
src/requests_extensions.adapters.egg-info/not-zip-safe
src/requests_extensions.adapters.egg-info/requires.txt
src/requests_extensions.adapters.egg-info/top_level.txt
src/requests_extensions/adapters/__init__.py
src/requests_extensions/adapters/core/__init__.py
src/tests/__init__.py
src/tests/test_core.py