Metadata-Version: 1.1
Name: requests-extensions.adapters
Version: 0.1.2
Summary: Adds dynamic loading and selection of adapters to requests
Home-page: https://github.com/robertpyke/requests_extensions.adapters
Author: Robert Pyke
Author-email: developer.robert.j.pyke@gmail.com
License: MIT
Platform: UNKNOWN
Classifier: Programming Language :: Python
